mixvideoconcat/__init__.py
mixvideoconcat/concat.py
mixvideoconcat/log.py
mixvideoconcat-1.3.0.dist-info/LICENSE
mixvideoconcat-1.3.0.dist-info/METADATA
mixvideoconcat-1.3.0.dist-info/WHEEL
mixvideoconcat-1.3.0.dist-info/entry_points.txt
mixvideoconcat-1.3.0.dist-info/top_level.txt
mixvideoconcat-1.3.0.dist-info/RECORD
