Metadata-Version: 2.1
Name: mixvideoconcat
Version: 1.3.0
Summary: Mixed videos concatenator
Author-email: Alexander Bushnev <Alexander@Bushnev.pro>
Maintainer-email: Alexander Bushnev <Alexander@Bushnev.pro>
License: GNU GENERAL PUBLIC LICENSE
Project-URL: Homepage, https://github.com/sashacmc/mixvideoconcat
Project-URL: Bug Reports, https://github.com/sashacmc/mixvideoconcat/issues
Project-URL: Source, https://github.com/sashacmc/mixvideoconcat/
Project-URL: Changelog, https://github.com/sashacmc/mixvideoconcat/blob/master/CHANGELOG.md
Keywords: video,concatenate,tool,ffmpeg
Classifier: Development Status :: 4 - Beta
Classifier: Operating System :: POSIX :: Linux
Classifier: Operating System :: MacOS
Classifier: Programming Language :: Python
Classifier: Programming Language :: Python :: 3
Classifier: Programming Language :: Python :: 3.6
Classifier: Programming Language :: Python :: 3.7
Classifier: Programming Language :: Python :: 3.8
Classifier: Programming Language :: Python :: 3.9
Classifier: Programming Language :: Python :: 3.10
Classifier: Programming Language :: Python :: 3.11
Classifier: License :: OSI Approved :: GNU General Public License v3 or later (GPLv3+)
Classifier: Topic :: Multimedia :: Video
Classifier: Topic :: Utilities
Requires-Python: >=3.8
License-File: LICENSE
